simpleval/__init__.py
simple_llm_eval-0.0.1.dist-info/METADATA
simple_llm_eval-0.0.1.dist-info/WHEEL
simple_llm_eval-0.0.1.dist-info/RECORD
