Metadata-Version: 2.3
Name: simple-llm-eval
Version: 0.0.1
Summary: Simple LLM Evaluation Using LLM As a Judge
License: Apache Software License (Apache-2.0)
Author: CyberArk
Author-email: acyberark@cyberark.com
Requires-Python: >=3.10.0,<4.0
Classifier: License :: Other/Proprietary License
Classifier: Programming Language :: Python :: 3
Classifier: Programming Language :: Python :: 3.10
Classifier: Programming Language :: Python :: 3.11
Classifier: Programming Language :: Python :: 3.12
Classifier: Programming Language :: Python :: 3.13
